{
  "_buildCommand2" : {
    "command" : "prepareForIndexing",
    "enableIndexBuildArena" : false,
    "targets" : null
  },
  "buildCommand" : "build",
  "configuredTargets" : [
    {
      "guid" : "7f36328153a7eb4f26498595e120f39b6fee50b2f81e8fd002f0c859a08741d7"
    },
    {
      "guid" : "7f36328153a7eb4f26498595e120f39bae3e5743a92606929e9fda8eb9e0528a"
    },
    {
      "guid" : "7f36328153a7eb4f26498595e120f39b3fd5cb7930a48d851ce94c75e786585e"
    },
    {
      "guid" : "7f36328153a7eb4f26498595e120f39b108032bc018e559c874d78952d951b7d"
    }
  ],
  "containerPath" : "/Users/bernardocohen/repos/library/cppTutorial4/cpp/XCode/cppTutorial4.xcodeproj",
  "continueBuildingAfterErrors" : true,
  "enableIndexBuildArena" : false,
  "hideShellScriptEnvironment" : false,
  "parameters" : {
    "action" : "build",
    "activeArchitecture" : "x86_64",
    "activeRunDestination" : {
      "disableOnlyActiveArch" : false,
      "platform" : "macosx",
      "sdk" : "macosx12.3",
      "sdkVariant" : "macos",
      "supportedArchitectures" : [
        "x86_64h",
        "x86_64"
      ],
      "targetArchitecture" : "x86_64"
    },
    "arenaInfo" : {
      "buildIntermediatesPath" : "",
      "buildProductsPath" : "",
      "derivedDataPath" : "/Users/bernardocohen/Library/Developer/Xcode/DerivedData",
      "indexDataStoreFolderPath" : "/Users/bernardocohen/Library/Developer/Xcode/DerivedData/cppTutorial4-bxhljvtjlowgqlghnjzvbyaiilav/Index/DataStore",
      "indexEnableDataStore" : true,
      "indexPCHPath" : "/Users/bernardocohen/Library/Developer/Xcode/DerivedData/cppTutorial4-bxhljvtjlowgqlghnjzvbyaiilav/Index/PrecompiledHeaders",
      "pchPath" : ""
    },
    "configurationName" : "Debug",
    "overrides" : {
      "synthesized" : {
        "table" : {
          "ENABLE_PREVIEWS" : "NO"
        }
      }
    }
  },
  "qos" : "default",
  "schemeCommand" : "launch",
  "schemeCommand2" : "launch",
  "shouldCollectMetrics" : false,
  "showNonLoggedProgress" : true,
  "useDryRun" : true,
  "useImplicitDependencies" : true,
  "useLegacyBuildLocations" : false,
  "useParallelTargets" : true
}